datasette_enrichments_gpt/__init__.py
datasette_enrichments_gpt/templates/enrichment-gpt.html
datasette_enrichments_gpt-0.5.dist-info/LICENSE
datasette_enrichments_gpt-0.5.dist-info/METADATA
datasette_enrichments_gpt-0.5.dist-info/WHEEL
datasette_enrichments_gpt-0.5.dist-info/entry_points.txt
datasette_enrichments_gpt-0.5.dist-info/top_level.txt
datasette_enrichments_gpt-0.5.dist-info/RECORD
