Metadata-Version: 2.1
Name: datasette-enrichments-gpt
Version: 0.5
Summary: Datasette enrichment for analyzing row data using OpenAI's GPT models
Author: Simon Willison
License: Apache-2.0
Project-URL: Homepage, https://github.com/datasette/datasette-enrichments-gpt
Project-URL: Changelog, https://github.com/datasette/datasette-enrichments-gpt/releases
Project-URL: Issues, https://github.com/datasette/datasette-enrichments-gpt/issues
Project-URL: CI, https://github.com/datasette/datasette-enrichments-gpt/actions
Classifier: Framework :: Datasette
Classifier: License :: OSI Approved :: Apache Software License
Requires-Python: >=3.8
License-File: LICENSE
Requires-Dist: datasette-enrichments >=0.4.1
Requires-Dist: sqlite-utils
Provides-Extra: test
Requires-Dist: datasette-test ; extra == 'test'
Requires-Dist: pytest ; extra == 'test'
Requires-Dist: pytest-asyncio ; extra == 'test'
Requires-Dist: pytest-recording ; extra == 'test'
